capthalline-0.1.0.dist-info/METADATA
capthalline-0.1.0.dist-info/WHEEL
capthalline/__init__.py
capthalline/__init__.pyi
capthalline/capthalline.cpython-312-darwin.so
capthalline/py.typed
capthalline-0.1.0.dist-info/RECORD
